requests_openapi/__init__.py
requests_openapi/core.py
requests_openapi/requestor.py
requests_openapi-1.0.6.dist-info/licenses/LICENSE
requests_openapi-1.0.6.dist-info/METADATA
requests_openapi-1.0.6.dist-info/WHEEL
requests_openapi-1.0.6.dist-info/top_level.txt
requests_openapi-1.0.6.dist-info/RECORD
