Metadata-Version: 2.4
Name: requests-openapi
Version: 1.0.6
Summary: RequestsOpenAPI is a python client library for OpenAPI 3.0
Home-page: https://github.com/wy-z/requests-openapi
Author: weiyang
Author-email: weiyang.ones@gmail.com
License: MIT
Classifier: License :: OSI Approved :: MIT License
Classifier: Programming Language :: Python
Classifier: Programming Language :: Python :: 3
License-File: LICENSE
Requires-Dist: requests
Requires-Dist: pyyaml
Requires-Dist: openapi-pydantic
Requires-Dist: jsonref
Provides-Extra: dev
Requires-Dist: ruff; extra == "dev"
Requires-Dist: mypy; extra == "dev"
Requires-Dist: pytest; extra == "dev"
Requires-Dist: responses; extra == "dev"
Requires-Dist: pytest-cov; extra == "dev"
Dynamic: author
Dynamic: author-email
Dynamic: classifier
Dynamic: description
Dynamic: description-content-type
Dynamic: home-page
Dynamic: license
Dynamic: license-file
Dynamic: provides-extra
Dynamic: requires-dist
Dynamic: summary
